{
  "$schema": "https://turbo.build/schema.json",
  "ui": "stream",
  "globalDependencies": ["apps/web/.env*"],
  "globalEnv": [
    "BETTER_AUTH_SECRET",
    "BETTER_AUTH_URL",
    "DATABASE_URL",
    "GITHUB_CLIENT_ID",
    "GITHUB_CLIENT_SECRET",
    "GITHUB_APP_ID",
    "GITHUB_APP_PRIVATE_KEY",
    "GITHUB_APP_SLUG"
  ],
  "tasks": {
    "transit": {
      "dependsOn": ["^transit"]
    },
    "dev": {
      "cache": false,
      "persistent": true
    },
    "build": {
      "dependsOn": ["^build"],
      "inputs": ["$TURBO_DEFAULT$", ".env*"],
      "outputs": ["dist/**", ".next/**"]
    },
    "typecheck": {
      "dependsOn": ["transit"],
      "outputs": [".cache/tsbuildinfo.json"]
    },
    "db:push": {
      "cache": false,
      "env": ["DATABASE_URL"]
    },
    "clean": {
      "cache": false
    }
  }
}
